campbells-0.3.0.dist-info/METADATA
campbells-0.3.0.dist-info/WHEEL
campbells-0.3.0.dist-info/entry_points.txt
campbells-0.3.0.dist-info/licenses/LICENSE
campbells/.pytest_cache/.gitignore
campbells/.pytest_cache/CACHEDIR.TAG
campbells/.pytest_cache/README.md
campbells/.pytest_cache/v/cache/lastfailed
campbells/.pytest_cache/v/cache/nodeids
campbells/.pytest_cache/v/cache/stepwise
campbells/__init__.py
campbells/builder/__init__.py
campbells/builder/_html5lib/__init__.py
campbells/builder/_html5lib/attrs.py
campbells/builder/_html5lib/element_and_text.py
campbells/builder/_html5lib/html5_support.py
campbells/builder/_html5lib/main.py
campbells/builder/_htmlparser/__init__.py
campbells/builder/_htmlparser/builder.py
campbells/builder/_htmlparser/parser.py
campbells/builder/_lxml/__init__.py
campbells/builder/_lxml/html_builder.py
campbells/builder/_lxml/util.py
campbells/builder/_lxml/xml_builder.py
campbells/builder/core/__init__.py
campbells/builder/core/features.py
campbells/builder/core/html_builder.py
campbells/builder/core/main.py
campbells/builder/core/parser_names.py
campbells/builder/core/registry.py
campbells/builder/core/sax_builder.py
campbells/builder/core/xml.py
campbells/css.py
campbells/dammit/__init__.py
campbells/dammit/dependency_resolution.py
campbells/dammit/detection.py
campbells/dammit/encodings.py
campbells/dammit/substitution.py
campbells/diagnose.py
campbells/element/.pytest_cache/.gitignore
campbells/element/.pytest_cache/CACHEDIR.TAG
campbells/element/.pytest_cache/README.md
campbells/element/.pytest_cache/v/cache/nodeids
campbells/element/.pytest_cache/v/cache/stepwise
campbells/element/__init__.py
campbells/element/attributes.py
campbells/element/encodings.py
campbells/element/tag_core.py
campbells/element/whitespace.py
campbells/formatter.py
campbells/main.py
campbells/tests/.pytest_cache/.gitignore
campbells/tests/.pytest_cache/CACHEDIR.TAG
campbells/tests/.pytest_cache/README.md
campbells/tests/.pytest_cache/v/cache/lastfailed
campbells/tests/.pytest_cache/v/cache/nodeids
campbells/tests/.pytest_cache/v/cache/stepwise
campbells/tests/__init__.py
campbells-0.3.0.dist-info/RECORD
