Metadata-Version: 2.1
Name: campbells
Version: 0.3.0
Summary: A condensed web scraping library.
Keywords: HTML XML parse soup
Author-Email: Louis Maddox <louismmx@gmail.com>
License: MIT
Classifier: Development Status :: 3 - Alpha
Classifier: Intended Audience :: Developers
Classifier: Natural Language :: English
Classifier: Topic :: Software Development :: Libraries
Classifier: Programming Language :: Python
Classifier: Programming Language :: Python :: 3.10
Classifier: Programming Language :: Python :: 3.11
Classifier: Topic :: Text Processing :: Markup :: HTML
Classifier: Topic :: Text Processing :: Markup :: SGML
Classifier: Topic :: Text Processing :: Markup :: XML
Project-URL: Homepage, https://github.com/lmmx/campbells
Project-URL: Repository, https://github.com/lmmx/campbells.git
Requires-Python: >=3.10
Requires-Dist: chinois>=0.2.0
Requires-Dist: html5lib>=1.1; extra == "html5lib"
Requires-Dist: lxml>=4.9.3; extra == "lxml"
Provides-Extra: html5lib
Provides-Extra: lxml
